geokube/__init__.py
geokube/version.py
geokube/backend/__init__.py
geokube/backend/base.py
geokube/backend/netcdf.py
geokube/core/__init__.py
geokube/core/agg_mixin.py
geokube/core/axis.py
geokube/core/bounds.py
geokube/core/cell_methods.py
geokube/core/coord_system.py
geokube/core/coordinate.py
geokube/core/datacube.py
geokube/core/dataset.py
geokube/core/domain.py
geokube/core/domainmixin.py
geokube/core/enums.py
geokube/core/errs.py
geokube/core/field.py
geokube/core/unit.py
geokube/core/variable.py
geokube/static/css/style.css
geokube/static/html/icons-svg-inline.html
geokube/utils/__init__.py
geokube/utils/attrs_encoding.py
geokube/utils/classproperty.py
geokube/utils/decorators.py
geokube/utils/formatting.py
geokube/utils/formatting_html.py
geokube/utils/hcube_logger.py
geokube/utils/indexer_dict.py
geokube/utils/log_utils.py
geokube/utils/serialization.py
geokube/utils/type_utils.py
geokube/utils/util_methods.py
geokube/utils/warnings.py
geokube-2025.7.2.dist-info/licenses/LICENSE
tests/__init__.py
tests/backend/__init__.py
tests/backend/test_netcdf.py
tests/core/__init__.py
tests/core/test_axis.py
tests/core/test_coordinate.py
tests/core/test_datacube.py
tests/core/test_dataset.py
tests/core/test_domain.py
tests/core/test_enums.py
tests/core/test_field.py
tests/core/test_unit.py
tests/core/test_variable.py
tests/fixtures/__init__.py
tests/fixtures/shapes.py
tests/fixtures/xarray.py
geokube-2025.7.2.dist-info/METADATA
geokube-2025.7.2.dist-info/WHEEL
geokube-2025.7.2.dist-info/top_level.txt
geokube-2025.7.2.dist-info/RECORD
