Metadata-Version: 2.4
Name: geokube
Version: 2025.7.2
Summary: a Python package based on xarray for GeoScience Data Analysis
Home-page: https://github.com/CMCC-Foundation/geokube
Author: geokube Contributors
Author-email: geokube@googlegroups.com
License: Apache License, Version 2.0
Classifier: Development Status :: 4 - Beta
Classifier: Environment :: Web Environment
Classifier: Intended Audience :: Science/Research
Classifier: License :: OSI Approved :: Apache Software License
Classifier: Natural Language :: English
Classifier: Operating System :: OS Independent
Classifier: Programming Language :: Python :: 3
Classifier: Topic :: Scientific/Engineering
Requires-Python: >=3.10
License-File: LICENSE
Requires-Dist: cf_units==3.3.0
Requires-Dist: cartopy
Requires-Dist: numpy==2.0.2
Requires-Dist: pandas==2.2.3
Requires-Dist: netCDF4==1.7.2
Requires-Dist: h5py==3.14.0
Requires-Dist: scipy
Requires-Dist: xarray==2025.6.1
Requires-Dist: dask==2025.5.1
Requires-Dist: geopandas
Requires-Dist: intake==2.0.7
Requires-Dist: hvplot
Requires-Dist: pytest
Requires-Dist: dask[distributed]
Requires-Dist: zarr==2.18.4
Requires-Dist: rioxarray
Requires-Dist: plotly
Requires-Dist: pyarrow
Requires-Dist: numcodecs==0.15.1
Requires-Dist: flox
Requires-Dist: cf-xarray==0.10.5
Requires-Dist: h5netcdf==1.6.1
Requires-Dist: kerchunk==0.2.7
Dynamic: author
Dynamic: author-email
Dynamic: classifier
Dynamic: description
Dynamic: description-content-type
Dynamic: home-page
Dynamic: license
Dynamic: license-file
Dynamic: requires-dist
Dynamic: requires-python
Dynamic: summary
